<layer>
  <name>sharing_vehicles</name>
  <id>LayerInfoImpl--1e02d99c:189997e81fa:-79df</id>
  <type>VECTOR</type>
  <defaultStyle>
    <id>StyleInfoImpl-113972e5:18a7881cbca:-7ff6</id>
  </defaultStyle>
  <styles class="linked-hash-set">
    <style>
      <id>StyleInfoImpl-582a934f:18c7db0b402:-4332</id>
    </style>
  </styles>
  <resource class="featureType">
    <id>FeatureTypeInfoImpl--1e02d99c:189997e81fa:-79e0</id>
  </resource>
  <attribution>
    <logoWidth>0</logoWidth>
    <logoHeight>0</logoHeight>
  </attribution>
  <dateCreated>2023-07-28 12:38:08.640 UTC</dateCreated>
  <dateModified>2025-02-06 15:39:15.315 UTC</dateModified>
</layer>