<GeoServerTileLayer>
  <id>LayerInfoImpl--61f921fe:19227952649:-7f66</id>
  <enabled>true</enabled>
  <inMemoryCached>true</inMemoryCached>
  <name>MobiData-BW:park-api_item</name>
  <mimeFormats>
    <string>application/vnd.mapbox-vector-tile</string>
  </mimeFormats>
  <gridSubsets>
    <gridSubset>
      <gridSetName>WebMercatorQuadx2</gridSetName>
      <minCachedLevel>6</minCachedLevel>
      <maxCachedLevel>15</maxCachedLevel>
    </gridSubset>
  </gridSubsets>
  <metaWidthHeight>
    <int>4</int>
    <int>4</int>
  </metaWidthHeight>
  <expireCache>60</expireCache>
  <expireClients>55</expireClients>
  <parameterFilters>
    <styleParameterFilter>
      <key>STYLES</key>
      <defaultValue></defaultValue>
      <allowedStyles class="java.util.Collections$UnmodifiableSet"/>
      <availableStyles class="sorted-set">
        <string>MobiData-BW:mdbw_park-api_sites_occupancy</string>
      </availableStyles>
      <defaultStyle>MobiData-BW:mdbw_park-api_parking-object</defaultStyle>
    </styleParameterFilter>
  </parameterFilters>
  <gutter>0</gutter>
  <cacheWarningSkips/>
</GeoServerTileLayer>